ricks_auth_service_client.py
ricks_auth_service_client-0.1.2.dist-info/WHEEL
ricks_auth_service_client-0.1.2.dist-info/METADATA
ricks_auth_service_client-0.1.2.dist-info/RECORD
