Metadata-Version: 2.1
Name: ricks-auth-service-client
Version: 0.1.2
Summary: Client library for my custom auth service
License: MIT
Author: Rick Henry
Author-email: rickhenry@rickhenry.dev
Requires-Python: >=3.6,<4.0
Classifier: License :: OSI Approved :: MIT License
Classifier: Programming Language :: Python :: 3
Classifier: Programming Language :: Python :: 3.6
Classifier: Programming Language :: Python :: 3.7
Classifier: Programming Language :: Python :: 3.8
Classifier: Programming Language :: Python :: 3.9
Requires-Dist: aiohttp (>=3.7.3,<4.0.0)
Requires-Dist: python-jwt (>=3.3.0,<4.0.0)
